cnvlnoise.py
convolved_noise-0.1.dist-info/licenses/LICENSE
convolved_noise-0.1.dist-info/METADATA
convolved_noise-0.1.dist-info/WHEEL
convolved_noise-0.1.dist-info/top_level.txt
convolved_noise-0.1.dist-info/RECORD
